rescalculator/README.md
rescalculator/__init__.py
rescalculator/bifeo3prb.py
rescalculator/cartoons.py
rescalculator/convert_theta.py
rescalculator/convres.py
rescalculator/convres_sma.py
rescalculator/lattice.py
rescalculator/lattice_calculator_old.py
rescalculator/lattice_calculator_procedural.py
rescalculator/lattice_calculator_procedural2.py
rescalculator/mycleanargs.py
rescalculator/mytile.py
rescalculator/numpyutils.py
rescalculator/prefbifeo3.py
rescalculator/prefdemo.py
rescalculator/prefdemo_bifeo3.py
rescalculator/rescalc.py
rescalculator/rescalc_batched.py
rescalculator/rescalc_torch.py
rescalculator/reslattice.py
rescalculator/respython.py
rescalculator/smabifeo3.py
rescalculator/smademo.py
rescalculator/sqwdemo.py
rescalculator/sqwdemo_bifeo3.py
rescalculator/testbifeo3.py
rescalculator/testconv.py
rescalculator/backends/__init__.py
rescalculator/backends/base.py
rescalculator/backends/numba_backend.py
rescalculator/backends/numpy_backend.py
rescalculator/backends/pytorch_backend.py
rescalculator-2.0.1.dist-info/METADATA
rescalculator-2.0.1.dist-info/WHEEL
rescalculator-2.0.1.dist-info/top_level.txt
rescalculator-2.0.1.dist-info/RECORD
