Metadata-Version: 2.4
Name: rescalculator
Version: 2.0.1
Summary: Triple-Axis Spectrometer Resolution Calculator with Numba/PyTorch acceleration
Author-email: William Ratcliff <william.ratcliff@nist.gov>
Maintainer-email: William Ratcliff <william.ratcliff@nist.gov>
License: MIT
Project-URL: Homepage, https://github.com/scattering/rescalculator
Project-URL: Repository, https://github.com/scattering/rescalculator
Project-URL: Issues, https://github.com/scattering/rescalculator/issues
Keywords: neutron scattering,triple-axis spectrometer,resolution,TAS,Cooper-Nathans,pyspinw
Classifier: Development Status :: 4 - Beta
Classifier: Intended Audience :: Science/Research
Classifier: License :: OSI Approved :: MIT License
Classifier: Operating System :: OS Independent
Classifier: Programming Language :: Python :: 3
Classifier: Programming Language :: Python :: 3.9
Classifier: Programming Language :: Python :: 3.10
Classifier: Programming Language :: Python :: 3.11
Classifier: Programming Language :: Python :: 3.12
Classifier: Topic :: Scientific/Engineering :: Physics
Requires-Python: >=3.9
Requires-Dist: numpy>=1.20
Requires-Dist: scipy>=1.7
Requires-Dist: icp-lattice-calculator>=0.1.1
Provides-Extra: fast
Requires-Dist: numba>=0.57; extra == "fast"
Provides-Extra: gpu
Requires-Dist: torch>=2.0; extra == "gpu"
Provides-Extra: all
Requires-Dist: numba>=0.57; extra == "all"
Requires-Dist: torch>=2.0; extra == "all"
Requires-Dist: pyspinw; extra == "all"
Requires-Dist: matplotlib; extra == "all"
Provides-Extra: dev
Requires-Dist: pytest; extra == "dev"
Requires-Dist: pytest-cov; extra == "dev"
Requires-Dist: black; extra == "dev"
Requires-Dist: isort; extra == "dev"
Requires-Dist: mypy; extra == "dev"
Requires-Dist: numba>=0.57; extra == "dev"
